miade/__init__.py
miade/annotators.py
miade/concept.py
miade/core.py
miade/dosage.py
miade/dosageextractor.py
miade/metaannotations.py
miade/note.py
miade/paragraph.py
miade/data/allergens_subset.csv
miade/data/allergy_type.csv
miade/data/historic.csv
miade/data/multiwords.csv
miade/data/negated.csv
miade/data/patterns.csv
miade/data/problem_blacklist.csv
miade/data/reactions_subset.csv
miade/data/regex_para_chunk.csv
miade/data/singlewords.csv
miade/data/suspected.csv
miade/data/valid_meds.csv
miade/data/vtm_to_text.csv
miade/data/vtm_to_vmp.csv
miade/drugdoseade/__init__.py
miade/drugdoseade/entities_refiner.py
miade/drugdoseade/pattern_matcher.py
miade/drugdoseade/preprocessor.py
miade/drugdoseade/utils.py
miade/model_builders/__init__.py
miade/model_builders/cdbbuilder.py
miade/model_builders/preprocess_elg.py
miade/model_builders/preprocess_fdb.py
miade/model_builders/preprocess_snomeduk.py
miade/model_builders/vocabbuilder.py
miade/utils/__init__.py
miade/utils/annotatorconfig.py
miade/utils/logger.py
miade/utils/metaannotationstypes.py
miade/utils/miade_cat.py
miade/utils/miade_meta_cat.py
miade/utils/modelfactory.py
scripts/build_model_pack.py
scripts/miade.py
miade-1.0.7.dist-info/LICENCE.md
miade-1.0.7.dist-info/METADATA
miade-1.0.7.dist-info/WHEEL
miade-1.0.7.dist-info/entry_points.txt
miade-1.0.7.dist-info/top_level.txt
miade-1.0.7.dist-info/RECORD
