Metadata-Version: 2.1
Name: miade
Version: 1.0.7
Summary: A set of tools for extracting formattable data from clinical notes stored in electronic health record systems.
Author-email: Jennifer Jiang-Kells <jennifer.jiang.13@ucl.ac.uk>, James Brandreth <j.brandreth@ucl.ac.uk>
Project-URL: Homepage, https://github.com/uclh-criu/miade
Project-URL: Documentation, https://uclh-criu.github.io/miade/
Keywords: nlp,natural-language-processing,ml,ehr,electronic-health-records,ai,health,healthcare
Classifier: Development Status :: 5 - Production/Stable
Classifier: Intended Audience :: Healthcare Industry
Classifier: License :: OSI Approved :: BSD License
Classifier: Programming Language :: Python :: 3
Classifier: Programming Language :: Python :: 3.8
Classifier: Programming Language :: Python :: 3.9
Classifier: Programming Language :: Python :: 3.10
Classifier: Programming Language :: Python :: 3.11
Classifier: Operating System :: OS Independent
Requires-Python: >=3.8
License-File: LICENCE.md
Requires-Dist: medcat ==1.9.3
Requires-Dist: spacy <3.5.0,>=3.4.2
Requires-Dist: numpy >=1.22.0
Requires-Dist: pandas >=1.4.2
Requires-Dist: gensim >=4.3.0
Requires-Dist: typer >=0.7.0
Requires-Dist: typing >=3.7.4
Requires-Dist: pathlib >=1.0.1
Requires-Dist: pydantic >=1.10.0
Requires-Dist: negspacy >=1.0.3
Provides-Extra: dashboard
Requires-Dist: streamlit >=1.20.0 ; extra == 'dashboard'
Requires-Dist: streamlit-aggrid >=0.3.4.post3 ; extra == 'dashboard'
Requires-Dist: spacy-streamlit >=1.0.5 ; extra == 'dashboard'
Requires-Dist: seaborn >=0.12.2 ; extra == 'dashboard'
Requires-Dist: python-dotenv >=1.0.0 ; extra == 'dashboard'
Provides-Extra: dev
Requires-Dist: pytest >=7.1.3 ; extra == 'dev'
Requires-Dist: ruff >=0.5.2 ; extra == 'dev'
